mtalg/__about__.py
mtalg/__init__.py
mtalg/__res/__init__.py
mtalg/alg/__init__.py
mtalg/alg/elementwise_algebra.py
mtalg/core/__init__.py
mtalg/core/threads.py
mtalg/random/__init__.py
mtalg/random/random_number_generators.py
mtalg/testing/__init__.py
mtalg/testing/benchmarks_em_algebra.py
mtalg/testing/benchmarks_rng.py
mtalg/testing/test_core.py
mtalg/testing/test_em_algebra.py
mtalg/testing/test_random.py
mtalg/testing/test_rng.py
mtalg/tools/__get_threads.py
mtalg/tools/__init__.py
mtalg/tools/__set_threads.py
mtalg-1.1.2.dist-info/LICENSE.txt
mtalg-1.1.2.dist-info/METADATA
mtalg-1.1.2.dist-info/WHEEL
mtalg-1.1.2.dist-info/top_level.txt
mtalg-1.1.2.dist-info/RECORD
