Metadata-Version: 2.1
Name: mtalg
Version: 1.1.2
Summary: A library for elementwise multithreaded algebra and multithreaded random number generation.
Home-page: https://github.com/WWakker/mtalg
Author: Wouter Wakker and Luca Mingarelli
Author-email: lucamingarelli@me.com
License: MIT
Project-URL: Documentation, https://mtalg.readthedocs.io/
Project-URL: GitHub, https://github.com/WWakker/mtalg/
Classifier: Programming Language :: Python :: 3
Classifier: License :: OSI Approved :: MIT License
Classifier: Operating System :: OS Independent
Requires-Python: >=3.6
License-File: LICENSE.txt
Requires-Dist: numpy >=1.17.0
Provides-Extra: full
Requires-Dist: numba ; extra == 'full'
